bmark/__init__.py
bmark/bench.py
bmark/plot.py
bmark/result.py
bmark_py-0.0.4.dist-info/LICENSE
bmark_py-0.0.4.dist-info/METADATA
bmark_py-0.0.4.dist-info/WHEEL
bmark_py-0.0.4.dist-info/top_level.txt
bmark_py-0.0.4.dist-info/RECORD
