Metadata-Version: 2.1
Name: bmark-py
Version: 0.0.4
Summary: Benchmarking tool
Home-page: https://github.com/hakonmh/bmark
Author: Håkon Magne Holmen
Author-email: haakonholmen@hotmail.com
License: MIT
Classifier: Development Status :: 3 - Alpha
Classifier: License :: OSI Approved :: MIT License
Classifier: Programming Language :: Python :: 3.5
Classifier: Programming Language :: Python :: 3.6
Classifier: Programming Language :: Python :: 3.7
Classifier: Programming Language :: Python :: 3.8
Classifier: Programming Language :: Python :: 3.9
Classifier: Programming Language :: Python :: 3.10
Classifier: Programming Language :: Python :: 3.11
Requires-Python: >=3.5
License-File: LICENSE
Requires-Dist: pandas
Requires-Dist: ipython
Requires-Dist: prettytable (>=3.5.0)
Requires-Dist: bokeh (>=3.0.0)
